helloworld/__init__.py
su_hang_test-0.0.1.dist-info/METADATA
su_hang_test-0.0.1.dist-info/WHEEL
su_hang_test-0.0.1.dist-info/entry_points.txt
su_hang_test-0.0.1.dist-info/top_level.txt
su_hang_test-0.0.1.dist-info/RECORD
