Metadata-Version: 2.1
Name: su-hang-test
Version: 0.0.1
Summary: hello world
Home-page: https://baidu.com
Author: Sherlock1024
Author-email: holmes1024@outlook.com
